fees/__init__.py
fees/trade/TradeFeeProvider.py
fees/trade/__init__.py
fees/trade/filter/TradeFeeFilter.py
fees/trade/filter/__init__.py
persuader_technology_automata_fees-0.1.5.dist-info/LICENSE
persuader_technology_automata_fees-0.1.5.dist-info/METADATA
persuader_technology_automata_fees-0.1.5.dist-info/WHEEL
persuader_technology_automata_fees-0.1.5.dist-info/top_level.txt
persuader_technology_automata_fees-0.1.5.dist-info/RECORD
