Metadata-Version: 2.1
Name: persuader-technology-automata-fees
Version: 0.1.5
Summary: Automata Fees
Author: Persuader Technology
Author-email: software@persuader.technology
License: UNLICENSE
Classifier: Programming Language :: Python :: 3
License-File: LICENSE
Requires-Dist: persuader-technology-automata-core (>=0.6.0)
Requires-Dist: persuader-technology-automata-fee-repository (>=0.1.1)
Requires-Dist: persuader-technology-automata-exchange-repository (>=0.3.0)
